mozregression/__init__.py
mozregression/approx_persist.py
mozregression/bisector.py
mozregression/branches.py
mozregression/bugzilla.py
mozregression/build_info.py
mozregression/build_range.py
mozregression/class_registry.py
mozregression/cli.py
mozregression/config.py
mozregression/dates.py
mozregression/download_manager.py
mozregression/errors.py
mozregression/fetch_build_info.py
mozregression/fetch_configs.py
mozregression/history.py
mozregression/json_pushes.py
mozregression/launchers.py
mozregression/log.py
mozregression/mach_interface.py
mozregression/main.py
mozregression/metrics.yaml
mozregression/network.py
mozregression/persist_limit.py
mozregression/pings.yaml
mozregression/releases.py
mozregression/tc_authenticate.py
mozregression/telemetry.py
mozregression/tempdir.py
mozregression/test_runner.py
mozregression/version.py
mozregression-7.0.0.dist-info/licenses/LICENSE
mozregression-7.0.0.dist-info/METADATA
mozregression-7.0.0.dist-info/WHEEL
mozregression-7.0.0.dist-info/entry_points.txt
mozregression-7.0.0.dist-info/top_level.txt
mozregression-7.0.0.dist-info/RECORD
